[
  {
    "name": "yabasou",
    "category": "basic",
    "path": "decomoji/basic/yabasou.png",
    "created": "v5.0.0"
  },
  {
    "name": "yamigahukai",
    "category": "basic",
    "path": "decomoji/basic/yamigahukai.png",
    "created": "v5.0.0"
  },
  {
    "name": "yannderu",
    "category": "basic",
    "path": "decomoji/basic/yannderu.png",
    "created": "v5.0.0"
  },
  {
    "name": "yarakasi",
    "category": "basic",
    "path": "decomoji/basic/yarakasi.png",
    "created": "v5.0.0"
  },
  {
    "name": "yaritai",
    "category": "basic",
    "path": "decomoji/basic/yaritai.png",
    "created": "v5.0.0"
  },
  {
    "name": "yattane",
    "category": "basic",
    "path": "decomoji/basic/yattane.png",
    "created": "v5.0.0"
  },
  {
    "name": "yatteiki",
    "category": "basic",
    "path": "decomoji/basic/yatteiki.png",
    "created": "v5.0.0"
  },
  {
    "name": "yazawaganannteiukana",
    "category": "basic",
    "path": "decomoji/basic/yazawaganannteiukana.png",
    "created": "v5.0.0"
  },
  {
    "name": "yokatta",
    "category": "basic",
    "path": "decomoji/basic/yokatta.png",
    "created": "v5.0.0"
  },
  {
    "name": "yokuwakaranaikedonaotta",
    "category": "basic",
    "path": "decomoji/basic/yokuwakaranaikedonaotta.png",
    "created": "v5.0.0"
  },
  {
    "name": "yomigaeruakumu",
    "category": "basic",
    "path": "decomoji/basic/yomigaeruakumu.png",
    "created": "v5.0.0"
  },
  {
    "name": "yorosiku",
    "category": "basic",
    "path": "decomoji/basic/yorosiku.png",
    "created": "v5.0.0"
  },
  {
    "name": "yoruhanero",
    "category": "basic",
    "path": "decomoji/basic/yoruhanero.png",
    "created": "v5.0.0"
  },
  {
    "name": "yosasou",
    "category": "basic",
    "path": "decomoji/basic/yosasou.png",
    "created": "v5.0.0"
  },
  {
    "name": "yumegaaru",
    "category": "basic",
    "path": "decomoji/basic/yumegaaru.png",
    "created": "v5.0.0"
  },
  {
    "name": "yurusite",
    "category": "basic",
    "path": "decomoji/basic/yurusite.png",
    "created": "v5.0.0"
  },
  {
    "name": "yuusyou",
    "category": "basic",
    "path": "decomoji/basic/yuusyou.png",
    "created": "v5.0.0"
  }
]
